fiable_db.py
fiable_db-0.3.0.dist-info/LICENCE
fiable_db-0.3.0.dist-info/METADATA
fiable_db-0.3.0.dist-info/WHEEL
fiable_db-0.3.0.dist-info/top_level.txt
fiable_db-0.3.0.dist-info/RECORD
