Metadata-Version: 2.1
Name: fiable-db
Version: 0.3.0
Summary: Immutable NoSQL database in a plain file 
Home-page: https://github.com/tanrax/fiableDB
Author: Andros Fenollosa
Author-email: andros@fenollosa.email
Keywords: database,immutable,nosql,json
Classifier: Programming Language :: Python :: 3
Classifier: License :: OSI Approved :: GNU General Public License v3 or later (GPLv3+)
Classifier: Operating System :: OS Independent
Requires-Python: >3.7
License-File: LICENCE
